README.md
setup.py
rbjbhub/__init__.py
rbjbhub/extension.py
rbjbhub.egg-info/PKG-INFO
rbjbhub.egg-info/SOURCES.txt
rbjbhub.egg-info/dependency_links.txt
rbjbhub.egg-info/entry_points.txt
rbjbhub.egg-info/not-zip-safe
rbjbhub.egg-info/requires.txt
rbjbhub.egg-info/top_level.txt