Metadata-Version: 1.1
Name: rbjbhub
Version: 1.0.1
Summary: JetBrains Hub Support for ReviewBoard
Home-page: https://keep.imfreedom.org/grim/reviewboard_jetbrains_hub
Author: Gary Kramlich
Author-email: grim@reaperworld.com
License: MIT
Platform: UNKNOWN
Classifier: Development Status :: 4 - Beta
Classifier: Framework :: Review Board
Classifier: Operating System :: OS Independent
Classifier: Programming Language :: Python
Classifier: License :: OSI Approved :: GNU General Public License v2 (GPLv2)
